odoo/addons/partner_category_multi_company_analytic/README.rst
odoo/addons/partner_category_multi_company_analytic/__init__.py
odoo/addons/partner_category_multi_company_analytic/__manifest__.py
odoo/addons/partner_category_multi_company_analytic/i18n/it.po
odoo/addons/partner_category_multi_company_analytic/i18n/partner_category_multi_company_analytic.pot
odoo/addons/partner_category_multi_company_analytic/models/__init__.py
odoo/addons/partner_category_multi_company_analytic/models/analytic_distribution_model.py
odoo/addons/partner_category_multi_company_analytic/readme/CONTRIBUTORS.rst
odoo/addons/partner_category_multi_company_analytic/readme/DESCRIPTION.rst
odoo/addons/partner_category_multi_company_analytic/static/description/icon.png
odoo/addons/partner_category_multi_company_analytic/static/description/index.html
odoo/addons/partner_category_multi_company_analytic/views/analytic_distribution_model_views.xml
odoo_addon_partner_category_multi_company_analytic-16.0.1.0.0.4.dist-info/METADATA
odoo_addon_partner_category_multi_company_analytic-16.0.1.0.0.4.dist-info/WHEEL
odoo_addon_partner_category_multi_company_analytic-16.0.1.0.0.4.dist-info/top_level.txt
odoo_addon_partner_category_multi_company_analytic-16.0.1.0.0.4.dist-info/RECORD
